nx100_remote_control/__init__.py
nx100_remote_control/module/Commands.py
nx100_remote_control/module/Gripper.py
nx100_remote_control/module/JointMove.py
nx100_remote_control/module/LinearMove.py
nx100_remote_control/module/MockResponse.py
nx100_remote_control/module/Socket.py
nx100_remote_control/module/Utils.py
nx100_remote_control/module/WebServer.py
nx100_remote_control/module/__init__.py
nx100_remote_control/module/xbox360_controller.py
nx100_remote_control/objects/Alarm.py
nx100_remote_control/objects/Command.py
nx100_remote_control/objects/CurrentPos.py
nx100_remote_control/objects/Gripper.py
nx100_remote_control/objects/IO.py
nx100_remote_control/objects/JobDetail.py
nx100_remote_control/objects/MoveJ.py
nx100_remote_control/objects/MoveL.py
nx100_remote_control/objects/Response.py
nx100_remote_control/objects/Status.py
nx100_remote_control/objects/Time.py
nx100_remote_control/objects/__init__.py
nx100_remote_control-1.0.3.dist-info/LICENSE
nx100_remote_control-1.0.3.dist-info/METADATA
nx100_remote_control-1.0.3.dist-info/WHEEL
nx100_remote_control-1.0.3.dist-info/top_level.txt
nx100_remote_control-1.0.3.dist-info/RECORD
