Metadata-Version: 2.1
Name: nx100-remote-control
Version: 1.0.3
Summary: Motoman NX100 remote control ability research library
Home-page: https://github.com/norkator/nx100-remote-control
Author: norkator
Author-email: nitramite@outlook.com
License: UNKNOWN
Project-URL: Issues, https://github.com/norkator/nx100-remote-control/issues
Platform: UNKNOWN
Classifier: Programming Language :: Python
Classifier: License :: OSI Approved :: GNU Affero General Public License v3
Classifier: Operating System :: OS Independent
Requires-Python: >=3.6
License-File: LICENSE
